do_util/__init__.py
cas_qweqweqweqwe3_util-0.1.0.dist-info/METADATA
cas_qweqweqweqwe3_util-0.1.0.dist-info/WHEEL
cas_qweqweqweqwe3_util-0.1.0.dist-info/RECORD
