Metadata-Version: 2.3
Name: cas-qweqweqweqwe3-util
Version: 0.1.0
Summary: Package for DO utilities
Author: cwhuang
Author-email: cwhuang@hkma.gov.hk
Requires-Python: >=3.12
Classifier: Programming Language :: Python :: 3
Classifier: Programming Language :: Python :: 3.12
Classifier: Programming Language :: Python :: 3.13
